checkpost/__init__.py
checkpost/middleware.py
checkpost-0.3.1.dist-info/licenses/LICENSE
checkpost-0.3.1.dist-info/METADATA
checkpost-0.3.1.dist-info/WHEEL
checkpost-0.3.1.dist-info/top_level.txt
checkpost-0.3.1.dist-info/RECORD
