Metadata-Version: 2.4
Name: checkpost
Version: 0.3.1
Summary: Detects and blocks spam and fraud in Django apps without CAPTCHAs, ensuring seamless user experience.
Author-email: Nezanuha <contact@nezanuha.com>
License-Expression: MIT
Project-URL: Homepage, https://github.com/nezanuha/checkpost
Project-URL: Repository, https://github.com/nezanuha/checkpost
Classifier: Framework :: Django
Classifier: Programming Language :: Python :: 3
Classifier: Operating System :: OS Independent
Requires-Python: >=3.7
License-File: LICENSE
Requires-Dist: Django>=3.2
Dynamic: license-file
